pyTQA/__init__.py
pyTQA/tqa.py
pyTQA-1.0.4.dist-info/LICENSE
pyTQA-1.0.4.dist-info/METADATA
pyTQA-1.0.4.dist-info/WHEEL
pyTQA-1.0.4.dist-info/top_level.txt
pyTQA-1.0.4.dist-info/RECORD
