Metadata-Version: 2.1
Name: pyTQA
Version: 1.0.4
Summary: Python Wrapper for the Image Owl Total QA
Home-page: https://github.com/imageowl/pyTQA.git
Author: Matt Whitaker
Author-email: whitaker@imageowl.com
License: UNKNOWN
Platform: UNKNOWN
Classifier: License :: OSI Approved :: MIT License
Classifier: Programming Language :: Python :: 3.6
Requires-Python: >=3.6
License-File: LICENSE
Requires-Dist: requests
Requires-Dist: python-dateutil
